odoo/addons/event_registration_multi_qty/README.rst
odoo/addons/event_registration_multi_qty/__init__.py
odoo/addons/event_registration_multi_qty/__manifest__.py
odoo/addons/event_registration_multi_qty/i18n/es.po
odoo/addons/event_registration_multi_qty/i18n/event_registration_multi_qty.pot
odoo/addons/event_registration_multi_qty/i18n/it.po
odoo/addons/event_registration_multi_qty/models/__init__.py
odoo/addons/event_registration_multi_qty/models/event.py
odoo/addons/event_registration_multi_qty/readme/CONFIGURE.rst
odoo/addons/event_registration_multi_qty/readme/CONTRIBUTORS.rst
odoo/addons/event_registration_multi_qty/readme/DESCRIPTION.rst
odoo/addons/event_registration_multi_qty/readme/USAGE.rst
odoo/addons/event_registration_multi_qty/static/description/icon.png
odoo/addons/event_registration_multi_qty/static/description/index.html
odoo/addons/event_registration_multi_qty/tests/__init__.py
odoo/addons/event_registration_multi_qty/tests/test_event_registration_multi_qty.py
odoo/addons/event_registration_multi_qty/views/event_view.xml
odoo14_addon_event_registration_multi_qty-14.0.1.0.1.dev9.dist-info/METADATA
odoo14_addon_event_registration_multi_qty-14.0.1.0.1.dev9.dist-info/WHEEL
odoo14_addon_event_registration_multi_qty-14.0.1.0.1.dev9.dist-info/top_level.txt
odoo14_addon_event_registration_multi_qty-14.0.1.0.1.dev9.dist-info/RECORD
